Workbook

Sheet Assumptions
A1: AURORA OUTDOOR SUPPLY CO. — MODEL ASSUMPTIONS
A2: Multi-Channel Outdoor Retailer | Three Statement Financial Model | All figures in $000s
D4: Historical Results | I4: Forecast Period
B5: Assumptions | C5: Notes | D5: FY21 | E5: FY22 | F5: FY23 | G5: FY24 | H5: FY25 | I5: FY26 | J5: FY27 | K5: FY28 | L5: FY29 | M5: FY30
B6: REVENUE
B7: Revenue Growth (YoY %) | C7: Overall store + online revenue | E7: 0.158 | F7: 0.112 | G7: 0.084 | H7: 0.059 | I7: 0.1 | J7: 0.1 | K7: 0.1 | L7: 0.08 | M7: 0.08
B8: Online Channel Mix (%) | C8: % of revenue via e-commerce | D8: 0.22 | E8: 0.25 | F8: 0.28 | G8: 0.3 | H8: 0.32 | I8: 0.34 | J8: 0.36 | K8: 0.38 | L8: 0.4 | M8: 0.42
B9: Store Channel Mix (%) | C9: % of revenue via physical stores | D9: 0.78 | E9: 0.75 | F9: 0.72 | G9: 0.7 | H9: 0.68 | I9: 0.66 | J9: 0.64 | K9: 0.62 | L9: 0.6 | M9: 0.58
B10: MARGINS
B11: Cost of Goods Sold (% Rev) | C11: Blended COGS across all channels | D11: 0.383 | E11: 0.407 | F11: 0.374 | G11: 0.37 | H11: 0.376 | I11: 0.37 | J11: 0.37 | K11: 0.37 | L11: 0.36 | M11: 0.36
B12: Gross Margin (%) | C12: Derived from model | D12: ='Three Statement Model'!D13 -> 0.61744782 | E12: ='Three Statement Model'!E13 -> 0.59348272 | F12: ='Three Statement Model'!F13 -> 0.62600023 | G12: ='Three Statement Model'!G13 -> 0.6300855 | H12: ='Three Statement Model'!H13 -> 0.62386915 | I12: ='Three Statement Model'!I13 -> 0.63 | J12: ='Three Statement Model'!J13 -> 0.63 | K12: ='Three Statement Model'!K13 -> 0.63 | ... M12: ='Three Statement Model'!M13 -> 0.64
B14: OPERATING EXPENSES
B15: Store Labour (% Rev) | C15: In-store staff wages & oncosts | D15: 0.13 | E15: 0.096 | F15: 0.091 | G15: 0.081 | H15: 0.084 | I15: 0.085 | J15: 0.085 | K15: 0.085 | L15: 0.08 | M15: 0.08
B16: Fulfilment & Logistics (% Rev) | C16: Online pick/pack & freight | D16: 0.04 | E16: 0.042 | F16: 0.043 | G16: 0.045 | H16: 0.046 | I16: 0.047 | J16: 0.047 | K16: 0.046 | L16: 0.045 | M16: 0.045
B17: Marketing & Promotions (% Rev) | C17: Paid, brand, catalogue | D17: 0.035 | E17: 0.038 | F17: 0.04 | G17: 0.038 | H17: 0.037 | I17: 0.04 | J17: 0.04 | K17: 0.038 | L17: 0.038 | M17: 0.038
B18: Rent & Occupancy ($000s) | C18: Fixed store leases + DC | D18: 10963 | E18: 10125 | F18: 10087 | G18: 11020 | H18: 11412 | I18: 12000 | J18: 12000 | K18: 13000 | L18: 13000 | M18: 14000
B19: G&A (% Rev) | C19: Corporate overhead | D19: 0.03 | E19: 0.025 | F19: 0.024 | G19: 0.022 | H19: 0.023 | I19: 0.023 | J19: 0.023 | K19: 0.023 | L19: 0.022 | M19: 0.022
B21: D&A & CAPEX
B22: Depreciation (% Opening PP&E) | C22: Straight-line on opening balance | D22: 0.429 | E22: 0.429 | F22: 0.429 | G22: 0.429 | H22: 0.429 | I22: 0.35 | J22: 0.35 | K22: 0.35 | L22: 0.35 | M22: 0.35
B23: Capital Expenditures ($000s) | C23: Store refits, IT, DC equipment | D23: 15000 | E23: 15000 | F23: 15000 | G23: 15000 | H23: 15000 | I23: 15000 | J23: 16000 | K23: 16000 | L23: 17000 | M23: 17000
B25: BALANCE SHEET
B26: Accounts Receivable (Days) | C26: Mostly wholesale; retail is near-zero | D26: 18 | E26: 18 | F26: 18 | G26: 18 | H26: 18 | I26: 18 | J26: 18 | K26: 18 | L26: 18 | M26: 18
B27: Inventory (Days) | C27: Days of COGS held; outdoor retail seasonal | D27: 73 | E27: 73 | F27: 73 | G27: 73 | H27: 73 | I27: 80 | J27: 85 | K27: 85 | L27: 85 | M27: 85
B28: Accounts Payable (Days) | C28: Supplier payment terms | D28: 36 | E28: 36 | F28: 36 | G28: 37 | H28: 36 | I28: 38 | J28: 38 | K28: 38 | L28: 38 | M28: 38
B30: FINANCING
B31: Interest Rate (% of Debt) | C31: Blended borrowing rate | D31: 0.05 | E31: 0.05 | F31: 0.05 | G31: 0.05 | H31: 0.05 | I31: 0.07 | J31: 0.07 | K31: 0.07 | L31: 0.07 | M31: 0.07
B32: Tax Rate (%) | C32: Effective corporate tax rate | D32: 0.31 | E32: 0.292 | F32: 0.287 | G32: 0.29 | H32: 0.291 | I32: 0.28 | J32: 0.28 | K32: 0.28 | L32: 0.28 | M32: 0.28
B33: Debt Issuance / (Repayment) ($000s) | C33: Planned debt movements | D33: 0 | E33: 0 | F33: -20000 | G33: 0 | H33: 0 | I33: 0 | J33: 0 | K33: 0 | L33: -10000 | M33: 0
B34: Equity Issued / (Repaid) ($000s) | C34: Equity raise or buyback | D34: 70000 | E34: 0 | F34: 0 | G34: 0 | H34: 0 | I34: 0 | J34: 0 | K34: 0 | L34: 0 | M34: 0
B35: Days in Year | D35: 365 | E35: 365 | F35: 365 | G35: 365 | H35: 365 | I35: 365 | J35: 365 | K35: 365 | L35: 365 | M35: 365
B38: COLOUR LEGEND
B39: Blue text = Hardcoded input (user-editable)
B40: Black text = Calculated formula
B41: Green text = Cross-sheet link

Sheet Three Statement Model
A1: AURORA OUTDOOR SUPPLY CO. — THREE STATEMENT MODEL
A2: Multi-Channel Outdoor Retailer | All figures in $000s unless noted | FY21-FY25 Historical | FY26-FY30 Forecast
C3: Balance Sheet Check → | D3: =IF(ABS(D42-D55)<1,"OK","ERROR") -> OK | E3: =IF(ABS(E42-E55)<1,"OK","ERROR") -> OK | F3: =IF(ABS(F42-F55)<1,"OK","ERROR") -> OK | G3: =IF(ABS(G42-G55)<1,"OK","ERROR") -> OK | H3: =IF(ABS(H42-H55)<1,"OK","ERROR") -> OK | I3: =IF(ABS(I42-I55)<1,"OK","ERROR") -> OK | J3: =IF(ABS(J42-J55)<1,"OK","ERROR") -> OK | K3: =IF(ABS(K42-K55)<1,"OK","ERROR") -> OK | ... M3: =IF(ABS(M42-M55)<1,"OK","ERROR") -> OK
D4: Historical Results | I4: Forecast Period
D5: FY21 | E5: FY22 | F5: FY23 | G5: FY24 | H5: FY25 | I5: FY26 | J5: FY27 | K5: FY28 | L5: FY29 | M5: FY30
C7: INCOME STATEMENT ($000s)
C8: Revenue ($000s) | D8: 102007 | E8: 118086 | F8: 131345 | G8: 142341 | H8: 150772 | I8: =H8*(1+Assumptions!I7) -> 165849.2 | J8: =I8*(1+Assumptions!J7) -> 182434.12 | K8: =J8*(1+Assumptions!K7) -> 200677.53 | L8: =K8*(1+Assumptions!L7) -> 216731.73 | M8: =L8*(1+Assumptions!M7) -> 234070.27
C9: Online Channel | D9: =D8*Assumptions!D8 -> 22441.54 | E9: =E8*Assumptions!E8 -> 29521.5 | F9: =F8*Assumptions!F8 -> 36776.6 | G9: =G8*Assumptions!G8 -> 42702.3 | H9: =H8*Assumptions!H8 -> 48247.04 | I9: =I8*Assumptions!I8 -> 56388.728 | J9: =J8*Assumptions!J8 -> 65676.283 | K9: =K8*Assumptions!K8 -> 76257.462 | ... M9: =M8*Assumptions!M8 -> 98309.515
C10: Store Channel | D10: =D8-D9 -> 79565.46 | E10: =E8-E9 -> 88564.5 | F10: =F8-F9 -> 94568.4 | G10: =G8-G9 -> 99638.7 | H10: =H8-H9 -> 102524.96 | I10: =I8-I9 -> 109460.47 | J10: =J8-J9 -> 116757.84 | K10: =K8-K9 -> 124420.07 | ... M10: =M8-M9 -> 135760.76
C11: Cost of Goods Sold | D11: 39023 | E11: 48004 | F11: 49123 | G11: 52654 | H11: 56710 | I11: =I8*Assumptions!I11 -> 61364.204 | J11: =J8*Assumptions!J11 -> 67500.624 | K11: =K8*Assumptions!K11 -> 74250.687 | L11: =L8*Assumptions!L11 -> 78023.424 | M11: =M8*Assumptions!M11 -> 84265.298
C12: Gross Profit | D12: 62984 | E12: 70082 | F12: 82222 | G12: 89687 | H12: 94062 | I12: =I8-I11 -> 104485 | J12: =J8-J11 -> 114933.5 | K12: =K8-K11 -> 126426.85 | L12: =L8-L11 -> 138708.31 | M12: =M8-M11 -> 149804.97
C13: Gross Margin (%) | D13: =IF(D8=0,"-",D12/D8) -> 0.61744782 | E13: =IF(E8=0,"-",E12/E8) -> 0.59348272 | F13: =IF(F8=0,"-",F12/F8) -> 0.62600023 | G13: =IF(G8=0,"-",G12/G8) -> 0.6300855 | H13: =IF(H8=0,"-",H12/H8) -> 0.62386915 | I13: =IF(I8=0,"-",I12/I8) -> 0.63 | J13: =IF(J8=0,"-",J12/J8) -> 0.63 | K13: =IF(K8=0,"-",K12/K8) -> 0.63 | ... M13: =IF(M8=0,"-",M12/M8) -> 0.64
C15: Operating Expenses
C16: Store Labour | D16: 13260.91 | E16: 11336.256 | F16: 11952.395 | G16: 11529.621 | H16: 12664.848 | I16: =I8*Assumptions!I15 -> 14097.182 | J16: =J8*Assumptions!J15 -> 15506.9 | K16: =K8*Assumptions!K15 -> 17057.59 | L16: =L8*Assumptions!L15 -> 17338.539 | M16: =M8*Assumptions!M15 -> 18725.622
C17: Fulfilment & Logistics | D17: 4080.28 | E17: 4959.612 | F17: 5647.835 | G17: 6405.345 | H17: 6935.512 | I17: =I8*Assumptions!I16 -> 7794.9124 | J17: =J8*Assumptions!J16 -> 8574.4036 | K17: =K8*Assumptions!K16 -> 9231.1665 | L17: =L8*Assumptions!L16 -> 9752.9281 | M17: =M8*Assumptions!M16 -> 10533.162
C18: Marketing & Promotions | D18: 3570.245 | E18: 4487.268 | F18: 5253.8 | G18: 5408.958 | H18: 5578.564 | I18: =I8*Assumptions!I17 -> 6633.968 | J18: =J8*Assumptions!J17 -> 7297.3648 | K18: =K8*Assumptions!K17 -> 7625.7462 | L18: =L8*Assumptions!L17 -> 8235.8059 | M18: =M8*Assumptions!M17 -> 8894.6704
C19: Rent & Occupancy | D19: 10963 | E19: 10125 | F19: 10087 | G19: 11020 | H19: 11412 | I19: =Assumptions!I18 -> 12000 | J19: =Assumptions!J18 -> 12000 | K19: =Assumptions!K18 -> 13000 | L19: =Assumptions!L18 -> 13000 | M19: =Assumptions!M18 -> 14000
C20: General & Administrative | D20: 3060.21 | E20: 2952.15 | F20: 3152.28 | G20: 3131.502 | H20: 3467.756 | I20: =I8*Assumptions!I19 -> 3814.5316 | J20: =J8*Assumptions!J19 -> 4195.9848 | K20: =K8*Assumptions!K19 -> 4615.5832 | L20: =L8*Assumptions!L19 -> 4768.0982 | M20: =M8*Assumptions!M19 -> 5149.546
C21: Depreciation & Amortisation | D21: 19500 | E21: 18150 | F21: 17205 | G21: 16544 | H21: 16080 | I21: =I93 -> 13132.35 | J21: =J93 -> 13786.028 | K21: =K93 -> 14560.918 | L21: =L93 -> 15064.597 | M21: =M93 -> 15741.988
C22: Total Operating Expenses | D22: =D16+D17+D18+D19+D20+D21 -> 54434.645 | E22: =E16+E17+E18+E19+E20+E21 -> 52010.286 | F22: =F16+F17+F18+F19+F20+F21 -> 53298.31 | G22: =G16+G17+G18+G19+G20+G21 -> 54039.426 | H22: =H16+H17+H18+H19+H20+H21 -> 56138.68 | I22: =I16+I17+I18+I19+I20+I21 -> 57472.944 | J22: =J16+J17+J18+J19+J20+J21 -> 61360.681 | K22: =K16+K17+K18+K19+K20+K21 -> 66091.004 | ... M22: =M16+M17+M18+M19+M20+M21 -> 73044.988
C24: EBIT | D24: =D12-D22 -> 8549.355 | E24: =E12-E22 -> 18071.714 | F24: =F12-F22 -> 28923.69 | G24: =G12-G22 -> 35647.574 | H24: =H12-H22 -> 37923.32 | I24: =I12-I22 -> 47012.052 | J24: =J12-J22 -> 53572.815 | K24: =K12-K22 -> 60335.841 | ... M24: =M12-M22 -> 76759.987
C25: EBIT Margin (%) | D25: =IF(D8=0,"-",D24/D8) -> 0.083811454 | E25: =IF(E8=0,"-",E24/E8) -> 0.15303858 | F25: =IF(F8=0,"-",F24/F8) -> 0.22021158 | G25: =IF(G8=0,"-",G24/G8) -> 0.25043785 | H25: =IF(H8=0,"-",H24/H8) -> 0.2515276 | I25: =IF(I8=0,"-",I24/I8) -> 0.28346264 | J25: =IF(J8=0,"-",J24/J8) -> 0.29365568 | K25: =IF(K8=0,"-",K24/K8) -> 0.30066067 | ... M25: =IF(M8=0,"-",M24/M8) -> 0.32793565
C27: Interest Expense | D27: 2500 | E27: 2500 | F27: 1500 | G27: 1500 | H27: 1500 | I27: =I100 -> 2100 | J27: =J100 -> 2100 | K27: =K100 -> 2100 | L27: =L100 -> 2100 | M27: =M100 -> 1400
C28: Earnings Before Tax | D28: =D24-D27 -> 6049.355 | E28: =E24-E27 -> 15571.714 | F28: =F24-F27 -> 27423.69 | G28: =G24-G27 -> 34147.574 | H28: =H24-H27 -> 36423.32 | I28: =I24-I27 -> 44912.052 | J28: =J24-J27 -> 51472.815 | K28: =K24-K27 -> 58235.841 | ... M28: =M24-M27 -> 75359.987
C29: Income Tax Expense | D29: 1120 | E29: 4858 | F29: 8483 | G29: 10908 | H29: 11598 | I29: =MAX(0,I28*Assumptions!I32) -> 12575.375 | J29: =MAX(0,J28*Assumptions!J32) -> 14412.388 | K29: =MAX(0,K28*Assumptions!K32) -> 16306.036 | L29: =MAX(0,L28*Assumptions!L32) -> 19165.536 | M29: =MAX(0,M28*Assumptions!M32) -> 21100.796
C30: Net Profit | D30: =D28-D29 -> 4929.355 | E30: =E28-E29 -> 10713.714 | F30: =F28-F29 -> 18940.69 | G30: =G28-G29 -> 23239.574 | H30: =H28-H29 -> 24825.32 | I30: =I28-I29 -> 32336.677 | J30: =J28-J29 -> 37060.427 | K30: =K28-K29 -> 41929.806 | ... M30: =M28-M29 -> 54259.19
C31: Net Margin (%) | D31: =IF(D8=0,"-",D30/D8) -> 0.048323693 | E31: =IF(E8=0,"-",E30/E8) -> 0.090728063 | F31: =IF(F8=0,"-",F30/F8) -> 0.14420564 | G31: =IF(G8=0,"-",G30/G8) -> 0.1632669 | H31: =IF(H8=0,"-",H30/H8) -> 0.16465471 | I31: =IF(I8=0,"-",I30/I8) -> 0.19497638 | J31: =IF(J8=0,"-",J30/J8) -> 0.20314416 | K31: =IF(K8=0,"-",K30/K8) -> 0.20894121 | ... M31: =IF(M8=0,"-",M30/M8) -> 0.23180727
C33: BALANCE SHEET ($000s)
C35: Assets
C36: Cash & Cash Equivalents | D36: 67971 | E36: 81210 | F36: 83715 | G36: 111070 | H36: 139549 | I36: =I79 -> 167988.08 | J36: =J79 -> 200385.87 | K36: =K79 -> 239107.73 | L36: =L79 -> 275177.62 | M36: =M79 -> 326519.99
C37: Accounts Receivable | D37: 5100 | E37: 5904 | F37: 6567 | G37: 7117 | H37: 7538 | I37: =I84 -> 8178.8647 | J37: =J84 -> 8996.7511 | K37: =K84 -> 9896.4262 | L37: =L84 -> 10688.14 | M37: =M84 -> 11543.192
C38: Inventory | D38: 7805 | E38: 9601 | F38: 9825 | G38: 10531 | H38: 11342 | I38: =I85 -> 13449.689 | J38: =J85 -> 15719.323 | K38: =K85 -> 17291.256 | L38: =L85 -> 18169.839 | M38: =M85 -> 19623.426
C39: Total Current Assets | D39: =D36+D37+D38 -> 80876 | E39: =E36+E37+E38 -> 96715 | F39: =F36+F37+F38 -> 100107 | G39: =G36+G37+G38 -> 128718 | H39: =H36+H37+H38 -> 158429 | I39: =I36+I37+I38 -> 189616.63 | J39: =J36+J37+J38 -> 225101.94 | K39: =K36+K37+K38 -> 266295.41 | ... M39: =M36+M37+M38 -> 357686.61
C41: Property, Plant & Equipment (net) | D41: 45500 | E41: 42350 | F41: 40145 | G41: 38601 | H41: 37521 | I41: =I94 -> 39388.65 | J41: =J94 -> 41602.622 | K41: =K94 -> 43041.705 | L41: =L94 -> 44977.108 | M41: =M94 -> 46235.12
C42: Total Assets | D42: =D39+D41 -> 126376 | E42: =E39+E41 -> 139065 | F42: =F39+F41 -> 140252 | G42: =G39+G41 -> 167319 | H42: =H39+H41 -> 195950 | I42: =I39+I41 -> 229005.28 | J42: =J39+J41 -> 266704.57 | K42: =K39+K41 -> 309337.12 | ... M42: =M39+M41 -> 403921.73
C44: Liabilities & Equity
C45: Accounts Payable | D45: 3902 | E45: 4800 | F45: 4912 | G45: 5266 | H45: 5670 | I45: =I86 -> 6388.6021 | J45: =J86 -> 7027.4623 | K45: =K86 -> 7730.2085 | L45: =L86 -> 8122.9867 | M45: =M86 -> 8772.8256
C46: Total Current Liabilities | D46: =D45 -> 3902 | E46: =E45 -> 4800 | F46: =F45 -> 4912 | G46: =G45 -> 5266 | H46: =H45 -> 5670 | I46: =I45 -> 6388.6021 | J46: =J45 -> 7027.4623 | K46: =K45 -> 7730.2085 | ... M46: =M45 -> 8772.8256
C48: Long-term Debt | D48: 50000 | E48: 50000 | F48: 30000 | G48: 30000 | H48: 30000 | I48: =I99 -> 30000 | J48: =J99 -> 30000 | K48: =K99 -> 30000 | L48: =L99 -> 20000 | M48: =M99 -> 20000
C49: Total Liabilities | D49: =D46+D48 -> 53902 | E49: =E46+E48 -> 54800 | F49: =F46+F48 -> 34912 | G49: =G46+G48 -> 35266 | H49: =H46+H48 -> 35670 | I49: =I46+I48 -> 36388.602 | J49: =J46+J48 -> 37027.462 | K49: =K46+K48 -> 37730.208 | ... M49: =M46+M48 -> 28772.826
C51: Share Capital | D51: 70000 | E51: 70000 | F51: 70000 | G51: 70000 | H51: 70000 | I51: =H51+Assumptions!I34 -> 70000 | J51: =I51+Assumptions!J34 -> 70000 | K51: =J51+Assumptions!K34 -> 70000 | L51: =K51+Assumptions!L34 -> 70000 | M51: =L51+Assumptions!M34 -> 70000
C52: Retained Earnings | D52: 2474 | E52: 14265 | F52: 35340 | G52: 62053 | H52: 90280 | I52: =H52+I30 -> 122616.68 | J52: =I52+J30 -> 159677.1 | K52: =J52+K30 -> 201606.91 | L52: =K52+L30 -> 250889.72 | M52: =L52+M30 -> 305148.91
C53: Total Shareholders' Equity | D53: =D51+D52 -> 72474 | E53: =E51+E52 -> 84265 | F53: =F51+F52 -> 105340 | G53: =G51+G52 -> 132053 | H53: =H51+H52 -> 160280 | I53: =I51+I52 -> 192616.68 | J53: =J51+J52 -> 229677.1 | K53: =K51+K52 -> 271606.91 | ... M53: =M51+M52 -> 375148.91
C55: Total Liabilities & Equity | D55: =D49+D53 -> 126376 | E55: =E49+E53 -> 139065 | F55: =F49+F53 -> 140252 | G55: =G49+G53 -> 167319 | H55: =H49+H53 -> 195950 | I55: =I49+I53 -> 229005.28 | J55: =J49+J53 -> 266704.57 | K55: =K49+K53 -> 309337.12 | ... M55: =M49+M53 -> 403921.73
C56: Balance Sheet Check | D56: =IF(ABS(D42-D55)<1,"OK","ERROR") -> OK | E56: =IF(ABS(E42-E55)<1,"OK","ERROR") -> OK | F56: =IF(ABS(F42-F55)<1,"OK","ERROR") -> OK | G56: =IF(ABS(G42-G55)<1,"OK","ERROR") -> OK | H56: =IF(ABS(H42-H55)<1,"OK","ERROR") -> OK | I56: =IF(ABS(I42-I55)<1,"OK","ERROR") -> OK | J56: =IF(ABS(J42-J55)<1,"OK","ERROR") -> OK | K56: =IF(ABS(K42-K55)<1,"OK","ERROR") -> OK | ... M56: =IF(ABS(M42-M55)<1,"OK","ERROR") -> OK
C58: CASH FLOW STATEMENT ($000s)
C60: Operating Activities
C61: Net Profit | D61: 2474 | E61: 11791 | F61: 21075 | G61: 26713 | H61: 28227 | I61: =I30 -> 32336.677 | J61: =J30 -> 37060.427 | K61: =K30 -> 41929.806 | L61: =L30 -> 49282.807 | M61: =M30 -> 54259.19
C62: Add: D&A | D62: 19500 | E62: 18150 | F62: 17205 | G62: 16544 | H62: 16080 | I62: =I21 -> 13132.35 | J62: =J21 -> 13786.028 | K62: =K21 -> 14560.918 | L62: =L21 -> 15064.597 | M62: =M21 -> 15741.988
C63: Change in Accounts Receivable | D63: 0 | E63: =-(E84-D84) -> -804 | F63: =-(F84-E84) -> -663 | G63: =-(G84-F84) -> -550 | H63: =-(H84-G84) -> -421 | I63: =-(I84-H84) -> -640.86466 | J63: =-(J84-I84) -> -817.88647 | K63: =-(K84-J84) -> -899.67511 | L63: =-(L84-K84) -> -791.7141 | M63: =-(M84-L84) -> -855.05123
C64: Change in Inventory | D64: 0 | E64: =-(E85-D85) -> -1796 | F64: =-(F85-E85) -> -224 | G64: =-(G85-F85) -> -706 | H64: =-(H85-G85) -> -811 | I64: =-(I85-H85) -> -2107.6885 | J64: =-(J85-I85) -> -2269.6349 | K64: =-(K85-J85) -> -1571.9323 | L64: =-(L85-K85) -> -878.58273 | M64: =-(M85-L85) -> -1453.5871
C65: Change in Accounts Payable | D65: 0 | E65: =E86-D86 -> 898 | F65: =F86-E86 -> 112 | G65: =G86-F86 -> 354 | H65: =H86-G86 -> 404 | I65: =I86-H86 -> 718.60206 | J65: =J86-I86 -> 638.86021 | K65: =K86-J86 -> 702.74623 | L65: =L86-K86 -> 392.77816 | M65: =M86-L86 -> 649.83893
C66: Cash from Operations | D66: =D61+D62+D63+D64+D65 -> 21974 | E66: =E61+E62+E63+E64+E65 -> 28239 | F66: =F61+F62+F63+F64+F65 -> 37505 | G66: =G61+G62+G63+G64+G65 -> 42355 | H66: =H61+H62+H63+H64+H65 -> 43479 | I66: =I61+I62+I63+I64+I65 -> 43439.076 | J66: =J61+J62+J63+J64+J65 -> 48397.793 | K66: =K61+K62+K63+K64+K65 -> 54721.862 | ... M66: =M61+M62+M63+M64+M65 -> 68342.379
C68: Investing Activities
C69: Capital Expenditures | D69: -15000 | E69: -15000 | F69: -15000 | G69: -15000 | H69: -15000 | I69: =-I92 -> -15000 | J69: =-J92 -> -16000 | K69: =-K92 -> -16000 | L69: =-L92 -> -17000 | M69: =-M92 -> -17000
C70: Cash from Investing | D70: =D69 -> -15000 | E70: =E69 -> -15000 | F70: =F69 -> -15000 | G70: =G69 -> -15000 | H70: =H69 -> -15000 | I70: =I69 -> -15000 | J70: =J69 -> -16000 | K70: =K69 -> -16000 | ... M70: =M69 -> -17000
C72: Financing Activities
C73: Debt Issuance / (Repayment) | D73: 0 | E73: 0 | F73: -20000 | G73: 0 | H73: 0 | I73: =I98 -> 0 | J73: =J98 -> 0 | K73: =K98 -> 0 | L73: =L98 -> -10000 | M73: =M98 -> 0
C74: Equity Issued / (Repaid) | D74: 70000 | E74: 0 | F74: 0 | G74: 0 | H74: 0 | I74: =Assumptions!I34 -> 0 | J74: =Assumptions!J34 -> 0 | K74: =Assumptions!K34 -> 0 | L74: =Assumptions!L34 -> 0 | M74: =Assumptions!M34 -> 0
C75: Cash from Financing | D75: =D73+D74 -> 70000 | E75: =E73+E74 -> 0 | F75: =F73+F74 -> -20000 | G75: =G73+G74 -> 0 | H75: =H73+H74 -> 0 | I75: =I73+I74 -> 0 | J75: =J73+J74 -> 0 | K75: =K73+K74 -> 0 | ... M75: =M73+M74 -> 0
C77: Net Increase / (Decrease) in Cash | D77: =D66+D70+D75 -> 76974 | E77: =E66+E70+E75 -> 13239 | F77: =F66+F70+F75 -> 2505 | G77: =G66+G70+G75 -> 27355 | H77: =H66+H70+H75 -> 28479 | I77: =I66+I70+I75 -> 28439.076 | J77: =J66+J70+J75 -> 32397.793 | K77: =K66+K70+K75 -> 38721.862 | ... M77: =M66+M70+M75 -> 51342.379
C78: Opening Cash Balance | D78: 0 | E78: 67971 | F78: 81210 | G78: 83715 | H78: 111070 | I78: =H79 -> 139549 | J78: =I79 -> 167988.08 | K78: =J79 -> 200385.87 | L78: =K79 -> 239107.73 | M78: =L79 -> 275177.62
C79: Closing Cash Balance | D79: =D78+D77 -> 76974 | E79: =E78+E77 -> 81210 | F79: =F78+F77 -> 83715 | G79: =G78+G77 -> 111070 | H79: =H78+H77 -> 139549 | I79: =I78+I77 -> 167988.08 | J79: =J78+J77 -> 200385.87 | K79: =K78+K77 -> 239107.73 | ... M79: =M78+M77 -> 326519.99
C81: SUPPORTING SCHEDULES ($000s)
C83: Working Capital Schedule
C84: Accounts Receivable | D84: 5100 | E84: 5904 | F84: 6567 | G84: 7117 | H84: 7538 | I84: =I8/365*Assumptions!I26 -> 8178.8647 | J84: =J8/365*Assumptions!J26 -> 8996.7511 | K84: =K8/365*Assumptions!K26 -> 9896.4262 | L84: =L8/365*Assumptions!L26 -> 10688.14 | M84: =M8/365*Assumptions!M26 -> 11543.192
C85: Inventory | D85: 7805 | E85: 9601 | F85: 9825 | G85: 10531 | H85: 11342 | I85: =I11/365*Assumptions!I27 -> 13449.689 | J85: =J11/365*Assumptions!J27 -> 15719.323 | K85: =K11/365*Assumptions!K27 -> 17291.256 | L85: =L11/365*Assumptions!L27 -> 18169.839 | M85: =M11/365*Assumptions!M27 -> 19623.426
C86: Accounts Payable | D86: 3902 | E86: 4800 | F86: 4912 | G86: 5266 | H86: 5670 | I86: =I11/365*Assumptions!I28 -> 6388.6021 | J86: =J11/365*Assumptions!J28 -> 7027.4623 | K86: =K11/365*Assumptions!K28 -> 7730.2085 | L86: =L11/365*Assumptions!L28 -> 8122.9867 | M86: =M11/365*Assumptions!M28 -> 8772.8256
C87: Net Working Capital | D87: =D84+D85-D86 -> 9003 | E87: =E84+E85-E86 -> 10705 | F87: =F84+F85-F86 -> 11480 | G87: =G84+G85-G86 -> 12382 | H87: =H84+H85-H86 -> 13210 | I87: =I84+I85-I86 -> 15239.951 | J87: =J84+J85-J86 -> 17688.612 | K87: =K84+K85-K86 -> 19457.474 | ... M87: =M84+M85-M86 -> 22393.792
C88: Change in NWC | D88: 9003 | E88: =E87-D87 -> 1702 | F88: =F87-E87 -> 775 | G88: =G87-F87 -> 902 | H88: =H87-G87 -> 828 | I88: =I87-H87 -> 2029.9511 | J88: =J87-I87 -> 2448.6612 | K88: =K87-J87 -> 1768.8612 | L88: =L87-K87 -> 1277.5187 | M88: =M87-L87 -> 1658.7994
C90: PP&E & Depreciation Schedule
C91: Opening PP&E | D91: 50000 | E91: 45500 | F91: 42350 | G91: 40145 | H91: 38601 | I91: =H94 -> 37521 | J91: =I94 -> 39388.65 | K91: =J94 -> 41602.622 | L91: =K94 -> 43041.705 | M91: =L94 -> 44977.108
C92: Plus: Capital Expenditures | D92: 15000 | E92: 15000 | F92: 15000 | G92: 15000 | H92: 15000 | I92: =Assumptions!I23 -> 15000 | J92: =Assumptions!J23 -> 16000 | K92: =Assumptions!K23 -> 16000 | L92: =Assumptions!L23 -> 17000 | M92: =Assumptions!M23 -> 17000
C93: Less: Depreciation | D93: 19500 | E93: 18150 | F93: 17205 | G93: 16544 | H93: 16080 | I93: =I91*Assumptions!I22 -> 13132.35 | J93: =J91*Assumptions!J22 -> 13786.028 | K93: =K91*Assumptions!K22 -> 14560.918 | L93: =L91*Assumptions!L22 -> 15064.597 | M93: =M91*Assumptions!M22 -> 15741.988
C94: Closing PP&E | D94: =D91+D92-D93 -> 45500 | E94: =E91+E92-E93 -> 42350 | F94: =F91+F92-F93 -> 40145 | G94: =G91+G92-G93 -> 38601 | H94: =H91+H92-H93 -> 37521 | I94: =I91+I92-I93 -> 39388.65 | J94: =J91+J92-J93 -> 41602.622 | K94: =K91+K92-K93 -> 43041.705 | ... M94: =M91+M92-M93 -> 46235.12
C96: Debt Schedule
C97: Opening Debt | D97: 50000 | E97: 50000 | F97: 50000 | G97: 30000 | H97: 30000 | I97: =H99 -> 30000 | J97: =I99 -> 30000 | K97: =J99 -> 30000 | L97: =K99 -> 30000 | M97: =L99 -> 20000
C98: Issuance / (Repayment) | D98: 0 | E98: 0 | F98: -20000 | G98: 0 | H98: 0 | I98: =Assumptions!I33 -> 0 | J98: =Assumptions!J33 -> 0 | K98: =Assumptions!K33 -> 0 | L98: =Assumptions!L33 -> -10000 | M98: =Assumptions!M33 -> 0
C99: Closing Debt | D99: =D97+D98 -> 50000 | E99: =E97+E98 -> 50000 | F99: =F97+F98 -> 30000 | G99: =G97+G98 -> 30000 | H99: =H97+H98 -> 30000 | I99: =I97+I98 -> 30000 | J99: =J97+J98 -> 30000 | K99: =K97+K98 -> 30000 | ... M99: =M97+M98 -> 20000
C100: Interest Expense | D100: 2500 | E100: 2500 | F100: 1500 | G100: 1500 | H100: 1500 | I100: =I97*Assumptions!I31 -> 2100 | J100: =J97*Assumptions!J31 -> 2100 | K100: =K97*Assumptions!K31 -> 2100 | L100: =L97*Assumptions!L31 -> 2100 | M100: =M97*Assumptions!M31 -> 1400
