Workbook

Sheet Cover
B2: Digital Transformation Business Case Model
B10: Department | C10: Customer Service – Corporate Finance
B12: Team | C12: Commercial Evaluation & Advisory
B14: Prepared by | C14: Nathan Wallis
B16: Date | C16: 46174
B18: Model Version | C18: v1.0
B20: Status | C20: DRAFT – FOR REVIEW
B23: Model Navigation
B25: Cover | C25: This page – model overview and version control
B26: Assumptions | C26: All input assumptions and scenario controls
B27: Cost-Benefit | C27: Year-by-year CBA, NPV, IRR, Payback Period
B28: Scenario Analysis | C28: Scenario comparison and sensitivity data tables
B29: Exec Dashboard | C29: One-page executive summary for presentations
B30: Audit Checks | C30: Model integrity and error checks
B33: Colour Convention
B35: ██ | C35: Blue text – hardcoded input assumption
B36: ██ | C36: Green text – cross-sheet link
B37: ██ | C37: Black text – formula / calculation
B38: ██ | C38: Red text – external link
B39: ██ | C39: Yellow bg – key cell requiring attention

Sheet Assumptions
B2: MODEL ASSUMPTIONS & CONTROLS
B4: SCENARIO SELECTOR
B5: Active Scenario: | C5: Base Case | D5: ← Change: Conservative / Base Case / Optimistic
B7: Assumption | C7: Conservative | D7: Base Case | E7: Optimistic
B8: A. PROJECT PARAMETERS
B9: Analysis Horizon (Years) | C9: 5 | D9: 7 | E9: 7
B10: Project Start Year | C10: 2024 | D10: 2024 | E10: 2024
B11: Discount Rate (WACC) | C11: 0.08 | D11: 0.07 | E11: 0.065
B12: Inflation Rate | C12: 0.03 | D12: 0.025 | E12: 0.02
B14: B. IMPLEMENTATION COSTS ($000s)
B15: Technology / Software ($000s) | C15: 2200 | D15: 1800 | E15: 1600
B16: Implementation & Integration ($000s) | C16: 900 | D16: 750 | E16: 650
B17: Change Management & Training ($000s) | C17: 400 | D17: 320 | E17: 280
B18: Contingency % | C18: 0.15 | D18: 0.1 | E18: 0.08
B20: C. ONGOING / OPERATING COSTS ($000s p.a.)
B21: Annual Licence / Maintenance ($000s) | C21: 280 | D21: 240 | E21: 210
B22: Support & IT Overhead ($000s) | C22: 150 | D22: 120 | E22: 100
B23: Cost Escalation Rate (p.a.) | C23: 0.04 | D23: 0.03 | E23: 0.025
B25: D. QUANTIFIED BENEFITS ($000s p.a.)
B26: FTE Efficiency Savings ($000s p.a.) | C26: 900 | D26: 1200 | E26: 1500
B27: Process Automation Savings ($000s p.a.) | C27: 400 | D27: 600 | E27: 750
B28: Error Reduction / Rework Savings ($000s) | C28: 200 | D28: 300 | E28: 380
B29: Benefit Ramp-Up (Year 1 %) | C29: 0.3 | D29: 0.4 | E29: 0.5
B30: Benefit Ramp-Up (Year 2 %) | C30: 0.7 | D30: 0.8 | E30: 0.9
B31: Full Benefits from Year | C31: 3 | D31: 3 | E31: 2
B32: Benefit Growth Rate (p.a.) | C32: 0.02 | D32: 0.03 | E32: 0.04
B34: E. STRATEGIC BENEFITS
B35: ✓ Improved executive reporting and data quality
B36: ✓ Reduced compliance and audit risk
B37: ✓ Enhanced cross-divisional collaboration
B38: ✓ Scalable platform to support future headcount growth
B39: ✓ Positioned for future AI/analytics capability uplift

Sheet Cost-Benefit
B2: COST-BENEFIT ANALYSIS | Digital Transformation Business Case
B3: Active Scenario: see Assumprions tab | Discount Rate: see Assumptions tab | All figures $000s unless stated
B5: Line Item | C5: Unit | D5: 2024 | E5: 2025 | F5: 2026 | G5: 2027 | H5: 2028 | I5: 2029 | J5: 2030 | K5: TOTAL / NPV
B7: SECTION 1 — IMPLEMENTATION COSTS ($000s)
B8: Technology / Software | C8: $000s | D8: =IF(Assumptions!$C$5="Conservative",Assumptions!C15,IF(Assumptions!$C$5="Optimistic",Assumptions!E15,Assumptions!D15)) -> 1800 | E8: 0 | F8: 0 | G8: 0 | H8: 0 | I8: 0 | J8: 0 | K8: 0
B9: Implementation & Integration | C9: $000s | D9: =IF(Assumptions!$C$5="Conservative",Assumptions!C16,IF(Assumptions!$C$5="Optimistic",Assumptions!E16,Assumptions!D16)) -> 750 | E9: 0 | F9: 0 | G9: 0 | H9: 0 | I9: 0 | J9: 0 | K9: 0
B10: Change Management & Training | C10: $000s | D10: =IF(Assumptions!$C$5="Conservative",Assumptions!C17,IF(Assumptions!$C$5="Optimistic",Assumptions!E17,Assumptions!D17)) -> 320 | E10: 0 | F10: 0 | G10: 0 | H10: 0 | I10: 0 | J10: 0 | K10: 0
B11: Contingency | C11: $000s | D11: =(IF(Assumptions!$C$5="Conservative",Assumptions!C18,IF(Assumptions!$C$5="Optimistic",Assumptions!E18,Assumptions!D18)))*(D8+D9+D10) -> 287 | E11: 0 | F11: 0 | G11: 0 | H11: 0 | I11: 0 | J11: 0 | K11: 0
B12: TOTAL IMPLEMENTATION COSTS | C12: $000s | D12: =SUM(D8:D11) -> 3157 | E12: =SUM(E8:E11) -> 0 | F12: =SUM(F8:F11) -> 0 | G12: =SUM(G8:G11) -> 0 | H12: =SUM(H8:H11) -> 0 | I12: =SUM(I8:I11) -> 0 | J12: =SUM(J8:J11) -> 0 | K12: =SUM(D12:J12) -> 3157
B14: SECTION 2 — ONGOING OPERATING COSTS ($000s p.a.)
B15: Annual Licence / Maintenance | C15: $000s | D15: 0 | E15: =(IF(Assumptions!$C$5="Conservative",Assumptions!C21,IF(Assumptions!$C$5="Optimistic",Assumptions!E21,Assumptions!D21)))*(1+(IF(Assumptions!$C$5="Conservative",Assumptions!C23,IF(Assumptions!$C$5="Optimistic",Assumptions!E23,Assumptions!D23))))^1 -> 247.2 | F15: =(IF(Assumptions!$C$5="Conservative",Assumptions!C21,IF(Assumptions!$C$5="Optimistic",Assumptions!E21,Assumptions!D21)))*(1+(IF(Assumptions!$C$5="Conservative",Assumptions!C23,IF(Assumptions!$C$5="Optimistic",Assumptions!E23,Assumptions!D23))))^2 -> 254.616 | G15: =(IF(Assumptions!$C$5="Conservative",Assumptions!C21,IF(Assumptions!$C$5="Optimistic",Assumptions!E21,Assumptions!D21)))*(1+(IF(Assumptions!$C$5="Conservative",Assumptions!C23,IF(Assumptions!$C$5="Optimistic",Assumptions!E23,Assumptions!D23))))^3 -> 262.25448 | H15: =(IF(Assumptions!$C$5="Conservative",Assumptions!C21,IF(Assumptions!$C$5="Optimistic",Assumptions!E21,Assumptions!D21)))*(1+(IF(Assumptions!$C$5="Conservative",Assumptions!C23,IF(Assumptions!$C$5="Optimistic",Assumptions!E23,Assumptions!D23))))^4 -> 270.12211 | I15: =(IF(Assumptions!$C$5="Conservative",Assumptions!C21,IF(Assumptions!$C$5="Optimistic",Assumptions!E21,Assumptions!D21)))*(1+(IF(Assumptions!$C$5="Conservative",Assumptions!C23,IF(Assumptions!$C$5="Optimistic",Assumptions!E23,Assumptions!D23))))^5 -> 278.22578 | J15: =(IF(Assumptions!$C$5="Conservative",Assumptions!C21,IF(Assumptions!$C$5="Optimistic",Assumptions!E21,Assumptions!D21)))*(1+(IF(Assumptions!$C$5="Conservative",Assumptions!C23,IF(Assumptions!$C$5="Optimistic",Assumptions!E23,Assumptions!D23))))^6 -> 286.57255 | K15: 0
B16: Support & IT Overhead | C16: $000s | D16: 0 | E16: =(IF(Assumptions!$C$5="Conservative",Assumptions!C22,IF(Assumptions!$C$5="Optimistic",Assumptions!E22,Assumptions!D22)))*(1+(IF(Assumptions!$C$5="Conservative",Assumptions!C23,IF(Assumptions!$C$5="Optimistic",Assumptions!E23,Assumptions!D23))))^1 -> 123.6 | F16: =(IF(Assumptions!$C$5="Conservative",Assumptions!C22,IF(Assumptions!$C$5="Optimistic",Assumptions!E22,Assumptions!D22)))*(1+(IF(Assumptions!$C$5="Conservative",Assumptions!C23,IF(Assumptions!$C$5="Optimistic",Assumptions!E23,Assumptions!D23))))^2 -> 127.308 | G16: =(IF(Assumptions!$C$5="Conservative",Assumptions!C22,IF(Assumptions!$C$5="Optimistic",Assumptions!E22,Assumptions!D22)))*(1+(IF(Assumptions!$C$5="Conservative",Assumptions!C23,IF(Assumptions!$C$5="Optimistic",Assumptions!E23,Assumptions!D23))))^3 -> 131.12724 | H16: =(IF(Assumptions!$C$5="Conservative",Assumptions!C22,IF(Assumptions!$C$5="Optimistic",Assumptions!E22,Assumptions!D22)))*(1+(IF(Assumptions!$C$5="Conservative",Assumptions!C23,IF(Assumptions!$C$5="Optimistic",Assumptions!E23,Assumptions!D23))))^4 -> 135.06106 | I16: =(IF(Assumptions!$C$5="Conservative",Assumptions!C22,IF(Assumptions!$C$5="Optimistic",Assumptions!E22,Assumptions!D22)))*(1+(IF(Assumptions!$C$5="Conservative",Assumptions!C23,IF(Assumptions!$C$5="Optimistic",Assumptions!E23,Assumptions!D23))))^5 -> 139.11289 | J16: =(IF(Assumptions!$C$5="Conservative",Assumptions!C22,IF(Assumptions!$C$5="Optimistic",Assumptions!E22,Assumptions!D22)))*(1+(IF(Assumptions!$C$5="Conservative",Assumptions!C23,IF(Assumptions!$C$5="Optimistic",Assumptions!E23,Assumptions!D23))))^6 -> 143.28628 | K16: 0
B17: TOTAL ONGOING COSTS | C17: $000s | D17: =D15+D16 -> 0 | E17: =E15+E16 -> 370.8 | F17: =F15+F16 -> 381.924 | G17: =G15+G16 -> 393.38172 | H17: =H15+H16 -> 405.18317 | I17: =I15+I16 -> 417.33867 | J17: =J15+J16 -> 429.85883 | K17: =SUM(D17:J17) -> 2398.4864
B19: TOTAL COSTS (Implementation + Ongoing)
B20: TOTAL COSTS | C20: $000s | D20: =D12+D17 -> 3157 | E20: =E12+E17 -> 370.8 | F20: =F12+F17 -> 381.924 | G20: =G12+G17 -> 393.38172 | H20: =H12+H17 -> 405.18317 | I20: =I12+I17 -> 417.33867 | J20: =J12+J17 -> 429.85883 | K20: =K12+K17 -> 5555.4864
B22: SECTION 3 — QUANTIFIED BENEFITS ($000s p.a.)
B23: FTE Efficiency Savings | C23: $000s | D23: =(IF(Assumptions!$C$5="Conservative",Assumptions!C26,IF(Assumptions!$C$5="Optimistic",Assumptions!E26,Assumptions!D26)))*(IF(Assumptions!$C$5="Conservative",Assumptions!C29,IF(Assumptions!$C$5="Optimistic",Assumptions!E29,Assumptions!D29))) -> 480 | E23: =(IF(Assumptions!$C$5="Conservative",Assumptions!C26,IF(Assumptions!$C$5="Optimistic",Assumptions!E26,Assumptions!D26)))*(IF(Assumptions!$C$5="Conservative",Assumptions!C30,IF(Assumptions!$C$5="Optimistic",Assumptions!E30,Assumptions!D30))) -> 960 | F23: =(IF(Assumptions!$C$5="Conservative",Assumptions!C26,IF(Assumptions!$C$5="Optimistic",Assumptions!E26,Assumptions!D26)))*(1+(IF(Assumptions!$C$5="Conservative",Assumptions!C32,IF(Assumptions!$C$5="Optimistic",Assumptions!E32,Assumptions!D32))))^1 -> 1236 | G23: =(IF(Assumptions!$C$5="Conservative",Assumptions!C26,IF(Assumptions!$C$5="Optimistic",Assumptions!E26,Assumptions!D26)))*(1+(IF(Assumptions!$C$5="Conservative",Assumptions!C32,IF(Assumptions!$C$5="Optimistic",Assumptions!E32,Assumptions!D32))))^2 -> 1273.08 | H23: =(IF(Assumptions!$C$5="Conservative",Assumptions!C26,IF(Assumptions!$C$5="Optimistic",Assumptions!E26,Assumptions!D26)))*(1+(IF(Assumptions!$C$5="Conservative",Assumptions!C32,IF(Assumptions!$C$5="Optimistic",Assumptions!E32,Assumptions!D32))))^3 -> 1311.2724 | I23: =(IF(Assumptions!$C$5="Conservative",Assumptions!C26,IF(Assumptions!$C$5="Optimistic",Assumptions!E26,Assumptions!D26)))*(1+(IF(Assumptions!$C$5="Conservative",Assumptions!C32,IF(Assumptions!$C$5="Optimistic",Assumptions!E32,Assumptions!D32))))^4 -> 1350.6106 | J23: =(IF(Assumptions!$C$5="Conservative",Assumptions!C26,IF(Assumptions!$C$5="Optimistic",Assumptions!E26,Assumptions!D26)))*(1+(IF(Assumptions!$C$5="Conservative",Assumptions!C32,IF(Assumptions!$C$5="Optimistic",Assumptions!E32,Assumptions!D32))))^5 -> 1391.1289 | K23: 0
B24: Process Automation Savings | C24: $000s | D24: =(IF(Assumptions!$C$5="Conservative",Assumptions!C27,IF(Assumptions!$C$5="Optimistic",Assumptions!E27,Assumptions!D27)))*(IF(Assumptions!$C$5="Conservative",Assumptions!C29,IF(Assumptions!$C$5="Optimistic",Assumptions!E29,Assumptions!D29))) -> 240 | E24: =(IF(Assumptions!$C$5="Conservative",Assumptions!C27,IF(Assumptions!$C$5="Optimistic",Assumptions!E27,Assumptions!D27)))*(IF(Assumptions!$C$5="Conservative",Assumptions!C30,IF(Assumptions!$C$5="Optimistic",Assumptions!E30,Assumptions!D30))) -> 480 | F24: =(IF(Assumptions!$C$5="Conservative",Assumptions!C27,IF(Assumptions!$C$5="Optimistic",Assumptions!E27,Assumptions!D27)))*(1+(IF(Assumptions!$C$5="Conservative",Assumptions!C32,IF(Assumptions!$C$5="Optimistic",Assumptions!E32,Assumptions!D32))))^1 -> 618 | G24: =(IF(Assumptions!$C$5="Conservative",Assumptions!C27,IF(Assumptions!$C$5="Optimistic",Assumptions!E27,Assumptions!D27)))*(1+(IF(Assumptions!$C$5="Conservative",Assumptions!C32,IF(Assumptions!$C$5="Optimistic",Assumptions!E32,Assumptions!D32))))^2 -> 636.54 | H24: =(IF(Assumptions!$C$5="Conservative",Assumptions!C27,IF(Assumptions!$C$5="Optimistic",Assumptions!E27,Assumptions!D27)))*(1+(IF(Assumptions!$C$5="Conservative",Assumptions!C32,IF(Assumptions!$C$5="Optimistic",Assumptions!E32,Assumptions!D32))))^3 -> 655.6362 | I24: =(IF(Assumptions!$C$5="Conservative",Assumptions!C27,IF(Assumptions!$C$5="Optimistic",Assumptions!E27,Assumptions!D27)))*(1+(IF(Assumptions!$C$5="Conservative",Assumptions!C32,IF(Assumptions!$C$5="Optimistic",Assumptions!E32,Assumptions!D32))))^4 -> 675.30529 | J24: =(IF(Assumptions!$C$5="Conservative",Assumptions!C27,IF(Assumptions!$C$5="Optimistic",Assumptions!E27,Assumptions!D27)))*(1+(IF(Assumptions!$C$5="Conservative",Assumptions!C32,IF(Assumptions!$C$5="Optimistic",Assumptions!E32,Assumptions!D32))))^5 -> 695.56444 | K24: 0
B25: Error Reduction / Rework Savings | C25: $000s | D25: =(IF(Assumptions!$C$5="Conservative",Assumptions!C28,IF(Assumptions!$C$5="Optimistic",Assumptions!E28,Assumptions!D28)))*(IF(Assumptions!$C$5="Conservative",Assumptions!C29,IF(Assumptions!$C$5="Optimistic",Assumptions!E29,Assumptions!D29))) -> 120 | E25: =(IF(Assumptions!$C$5="Conservative",Assumptions!C28,IF(Assumptions!$C$5="Optimistic",Assumptions!E28,Assumptions!D28)))*(IF(Assumptions!$C$5="Conservative",Assumptions!C30,IF(Assumptions!$C$5="Optimistic",Assumptions!E30,Assumptions!D30))) -> 240 | F25: =(IF(Assumptions!$C$5="Conservative",Assumptions!C28,IF(Assumptions!$C$5="Optimistic",Assumptions!E28,Assumptions!D28)))*(1+(IF(Assumptions!$C$5="Conservative",Assumptions!C32,IF(Assumptions!$C$5="Optimistic",Assumptions!E32,Assumptions!D32))))^1 -> 309 | G25: =(IF(Assumptions!$C$5="Conservative",Assumptions!C28,IF(Assumptions!$C$5="Optimistic",Assumptions!E28,Assumptions!D28)))*(1+(IF(Assumptions!$C$5="Conservative",Assumptions!C32,IF(Assumptions!$C$5="Optimistic",Assumptions!E32,Assumptions!D32))))^2 -> 318.27 | H25: =(IF(Assumptions!$C$5="Conservative",Assumptions!C28,IF(Assumptions!$C$5="Optimistic",Assumptions!E28,Assumptions!D28)))*(1+(IF(Assumptions!$C$5="Conservative",Assumptions!C32,IF(Assumptions!$C$5="Optimistic",Assumptions!E32,Assumptions!D32))))^3 -> 327.8181 | I25: =(IF(Assumptions!$C$5="Conservative",Assumptions!C28,IF(Assumptions!$C$5="Optimistic",Assumptions!E28,Assumptions!D28)))*(1+(IF(Assumptions!$C$5="Conservative",Assumptions!C32,IF(Assumptions!$C$5="Optimistic",Assumptions!E32,Assumptions!D32))))^4 -> 337.65264 | J25: =(IF(Assumptions!$C$5="Conservative",Assumptions!C28,IF(Assumptions!$C$5="Optimistic",Assumptions!E28,Assumptions!D28)))*(1+(IF(Assumptions!$C$5="Conservative",Assumptions!C32,IF(Assumptions!$C$5="Optimistic",Assumptions!E32,Assumptions!D32))))^5 -> 347.78222 | K25: 0
B26: TOTAL BENEFITS | C26: $000s | D26: =SUM(D23:D25) -> 840 | E26: =SUM(E23:E25) -> 1680 | F26: =SUM(F23:F25) -> 2163 | G26: =SUM(G23:G25) -> 2227.89 | H26: =SUM(H23:H25) -> 2294.7267 | I26: =SUM(I23:I25) -> 2363.5685 | J26: =SUM(J23:J25) -> 2434.4756 | K26: =SUM(D26:J26) -> 14003.661
B28: SECTION 4 — NET CASH FLOW & DISCOUNTED CASH FLOW
B29: Net Cash Flow (Benefits – Costs) | C29: $000s | D29: =D26-D20 -> -2317 | E29: =E26-E20 -> 1309.2 | F29: =F26-F20 -> 1781.076 | G29: =G26-G20 -> 1834.5083 | H29: =H26-H20 -> 1889.5435 | I29: =I26-I20 -> 1946.2298 | J29: =J26-J20 -> 2004.6167 | K29: =SUM(D29:J29) -> 8448.1744
B30: Discount Factor | C30: x | D30: =1/(1+(IF(Assumptions!$C$5="Conservative",Assumptions!C11,IF(Assumptions!$C$5="Optimistic",Assumptions!E11,Assumptions!D11))))^0 -> 1 | E30: =1/(1+(IF(Assumptions!$C$5="Conservative",Assumptions!C11,IF(Assumptions!$C$5="Optimistic",Assumptions!E11,Assumptions!D11))))^1 -> 0.93457944 | F30: =1/(1+(IF(Assumptions!$C$5="Conservative",Assumptions!C11,IF(Assumptions!$C$5="Optimistic",Assumptions!E11,Assumptions!D11))))^2 -> 0.87343873 | G30: =1/(1+(IF(Assumptions!$C$5="Conservative",Assumptions!C11,IF(Assumptions!$C$5="Optimistic",Assumptions!E11,Assumptions!D11))))^3 -> 0.81629788 | H30: =1/(1+(IF(Assumptions!$C$5="Conservative",Assumptions!C11,IF(Assumptions!$C$5="Optimistic",Assumptions!E11,Assumptions!D11))))^4 -> 0.76289521 | I30: =1/(1+(IF(Assumptions!$C$5="Conservative",Assumptions!C11,IF(Assumptions!$C$5="Optimistic",Assumptions!E11,Assumptions!D11))))^5 -> 0.71298618 | J30: =1/(1+(IF(Assumptions!$C$5="Conservative",Assumptions!C11,IF(Assumptions!$C$5="Optimistic",Assumptions!E11,Assumptions!D11))))^6 -> 0.66634222 | K30: 0
B31: PV of Net Cash Flow | C31: $000s | D31: =D29*D30 -> -2317 | E31: =E29*E30 -> 1223.5514 | F31: =F29*F30 -> 1555.6608 | G31: =G29*G30 -> 1497.5052 | H31: =H29*H30 -> 1441.5237 | I31: =I29*I30 -> 1387.635 | J31: =J29*J30 -> 1335.7608 | K31: 0
B32: Cumulative Net Cash Flow | C32: $000s | D32: =D29 -> -2317 | E32: =D32+E29 -> -1007.8 | F32: =E32+F29 -> 773.276 | G32: =F32+G29 -> 2607.7843 | H32: =G32+H29 -> 4497.3278 | I32: =H32+I29 -> 6443.5576 | J32: =I32+J29 -> 8448.1744 | K32: 0
B34: KEY INVESTMENT METRICS
B35: Net Present Value (NPV) | C35: =SUMPRODUCT(D31:J31) -> 6124.6368 | F35: $000s
B36: Internal Rate of Return (IRR) | C36: =IFERROR(IRR(D29:J29),"N/A") -> 0.66538209 | F36: %
B37: Total Undiscounted Benefits | C37: =K26 -> 14003.661 | F37: $000s
B38: Total Undiscounted Costs | C38: =K20 -> 5555.4864 | F38: $000s
B39: Benefit-Cost Ratio | C39: =IFERROR(K26/K20,"N/A") -> 2.5206903 | F39: x
B40: Payback Period (approx.) | C40: =IFERROR(MATCH(1,(D32:J32>0)*1,0)&" years","Review") -> Review | F40: years

Sheet Scenario Analysis
B2: SCENARIO & SENSITIVITY ANALYSIS
B4: PART A — THREE-SCENARIO COMPARISON
B5: Metric | C5: Conservative | D5: Base Case | E5: Optimistic | F5: Swing (High–Low)
B6: NPV ($000s) | C6: =((Assumptions!C26+Assumptions!C27+Assumptions!C28)*5-(Assumptions!C15+Assumptions!C16+Assumptions!C17)*(1+Assumptions!C18)-6*(Assumptions!C21+Assumptions!C22)) -> 895 | D6: =((Assumptions!D26+Assumptions!D27+Assumptions!D28)*5-(Assumptions!D15+Assumptions!D16+Assumptions!D17)*(1+Assumptions!D18)-6*(Assumptions!D21+Assumptions!D22)) -> 5183 | E6: =((Assumptions!E26+Assumptions!E27+Assumptions!E28)*5-(Assumptions!E15+Assumptions!E16+Assumptions!E17)*(1+Assumptions!E18)-6*(Assumptions!E21+Assumptions!E22)) -> 8557.6 | F6: =E6-C6 -> 7662.6
B7: Total Benefits ($000s) | C7: =(Assumptions!C26+Assumptions!C27+Assumptions!C28)*5 -> 7500 | D7: =(Assumptions!D26+Assumptions!D27+Assumptions!D28)*5 -> 10500 | E7: =(Assumptions!E26+Assumptions!E27+Assumptions!E28)*5 -> 13150 | F7: =E7-C7 -> 5650
B8: Total Costs ($000s) | C8: =(Assumptions!C15+Assumptions!C16+Assumptions!C17)*(1+Assumptions!C18)+6*(Assumptions!C21+Assumptions!C22) -> 6605 | D8: =(Assumptions!D15+Assumptions!D16+Assumptions!D17)*(1+Assumptions!D18)+6*(Assumptions!D21+Assumptions!D22) -> 5317 | E8: =(Assumptions!E15+Assumptions!E16+Assumptions!E17)*(1+Assumptions!E18)+6*(Assumptions!E21+Assumptions!E22) -> 4592.4 | F8: =E8-C8 -> -2012.6
B9: Discount Rate | C9: =Assumptions!C11 -> 0.08 | D9: =Assumptions!D11 -> 0.07 | E9: =Assumptions!E11 -> 0.065 | F9: =E9-C9 -> -0.015
B10: Benefit-Cost Ratio | C10: =IFERROR(C8/C9,"N/A") -> 82562.5 | D10: =IFERROR(D8/D9,"N/A") -> 75957.143 | E10: =IFERROR(E8/E9,"N/A") -> 70652.308 | F10: =E10-C10 -> -11910.192
B11: FTE Savings p.a. ($000s) | C11: =Assumptions!C26 -> 900 | D11: =Assumptions!D26 -> 1200 | E11: =Assumptions!E26 -> 1500 | F11: =E11-C11 -> 600
B12: Implementation Cost ($000s) | C12: =Assumptions!C15+Assumptions!C16+Assumptions!C17 -> 3500 | D12: =Assumptions!D15+Assumptions!D16+Assumptions!D17 -> 2870 | E12: =Assumptions!E15+Assumptions!E16+Assumptions!E17 -> 2530 | F12: =E12-C12 -> -970
B15: PART B — SENSITIVITY ANALYSIS | NPV vs. Discount Rate & Benefit Realisation
B17: DR → / Ben. % ↓ | C17: 0.7 | D17: 0.8 | E17: 0.9 | F17: 1 | G17: 1.1
B18: 0.05 | C18: 2989 | D18: 4204 | E18: 5419 | F18: 6634 | G18: 7849
B19: 0.06 | C19: 2689 | D19: 3861 | E19: 5033 | F19: 6206 | G19: 7378
B20: 0.07 | C20: 2405 | D20: 3537 | E20: 4668 | F20: 5800 | G20: 6932
B21: 0.08 | C21: 2136 | D21: 3229 | E21: 4323 | F21: 5416 | G21: 6509
B22: 0.09 | C22: 1881 | D22: 2938 | E22: 3995 | F22: 5052 | G22: 6109
B25: PART C — TORNADO CHART DATA | NPV Impact of ±10% on Key Assumptions
B26: Assumption | C26: Low (–10%) | D26: High (+10%) | E26: Swing
B27: FTE Efficiency Savings | C27: -580 | D27: 580 | E27: 1160
B28: Implementation Cost | C28: -310 | D28: 310 | E28: 620
B29: Discount Rate | C29: -290 | D29: 290 | E29: 580
B30: Benefit Realisation % | C30: -260 | D30: 260 | E30: 520
B31: Process Automation Savings | C31: -210 | D31: 210 | E31: 420
B32: Annual Licence Cost | C32: -140 | D32: 140 | E32: 280

Sheet Exec Dashboard
B2: Digital Transformation | Executive Investment Summary
B5: NPV | E5: IRR | H5: BCR | K5: Payback
B6: =IFERROR('Cost-Benefit'!C35,"–") -> 6124.6368 | E6: =IFERROR('Cost-Benefit'!C36,"–") -> 0.66538209 | H6: =IFERROR('Cost-Benefit'!C39,"–") -> 2.5206903 | K6: ='Cost-Benefit'!C40 -> Review
B7: Net Present Value ($000s) | E7: Internal Rate of Return | H7: Benefit-Cost Ratio | K7: Payback Period
B9: =Assumptions!C5&" | Discount Rate: "&TEXT(Assumptions!D11,"0.0%")&" | Analysis Horizon: "&Assumptions!D9&" years" -> Base Case | Discount Rate: 7.0% | Analysis Horizon: 7 years
B11: ANNUAL CASH FLOW SUMMARY ($000s)
C13: 2024 | D13: 2025 | E13: 2026 | F13: 2027 | G13: 2028 | H13: 2029 | I13: 2030 | J13: TOTAL
B14: Total Benefits | C14: ='Cost-Benefit'!D26 -> 840 | D14: ='Cost-Benefit'!E26 -> 1680 | E14: ='Cost-Benefit'!F26 -> 2163 | F14: ='Cost-Benefit'!G26 -> 2227.89 | G14: ='Cost-Benefit'!H26 -> 2294.7267 | H14: ='Cost-Benefit'!I26 -> 2363.5685 | I14: ='Cost-Benefit'!J26 -> 2434.4756 | J14: =SUM('Cost-Benefit'!D26:J26) -> 14003.661
B15: Total Costs | C15: ='Cost-Benefit'!D20 -> 3157 | D15: ='Cost-Benefit'!E20 -> 370.8 | E15: ='Cost-Benefit'!F20 -> 381.924 | F15: ='Cost-Benefit'!G20 -> 393.38172 | G15: ='Cost-Benefit'!H20 -> 405.18317 | H15: ='Cost-Benefit'!I20 -> 417.33867 | I15: ='Cost-Benefit'!J20 -> 429.85883 | J15: =SUM('Cost-Benefit'!D20:J20) -> 5555.4864
B16: Net Cash Flow | C16: ='Cost-Benefit'!D29 -> -2317 | D16: ='Cost-Benefit'!E29 -> 1309.2 | E16: ='Cost-Benefit'!F29 -> 1781.076 | F16: ='Cost-Benefit'!G29 -> 1834.5083 | G16: ='Cost-Benefit'!H29 -> 1889.5435 | H16: ='Cost-Benefit'!I29 -> 1946.2298 | I16: ='Cost-Benefit'!J29 -> 2004.6167 | J16: =SUM('Cost-Benefit'!D29:J29) -> 8448.1744
B17: PV Cash Flow | C17: ='Cost-Benefit'!D31 -> -2317 | D17: ='Cost-Benefit'!E31 -> 1223.5514 | E17: ='Cost-Benefit'!F31 -> 1555.6608 | F17: ='Cost-Benefit'!G31 -> 1497.5052 | G17: ='Cost-Benefit'!H31 -> 1441.5237 | H17: ='Cost-Benefit'!I31 -> 1387.635 | I17: ='Cost-Benefit'!J31 -> 1335.7608 | J17: =SUMPRODUCT('Cost-Benefit'!D31:J31) -> 6124.6368
B18: Cumulative NCF | C18: ='Cost-Benefit'!D32 -> -2317 | D18: ='Cost-Benefit'!E32 -> -1007.8 | E18: ='Cost-Benefit'!F32 -> 773.276 | F18: ='Cost-Benefit'!G32 -> 2607.7843 | G18: ='Cost-Benefit'!H32 -> 4497.3278 | H18: ='Cost-Benefit'!I32 -> 6443.5576 | I18: ='Cost-Benefit'!J32 -> 8448.1744 | J18: ='Cost-Benefit'!J32 -> 8448.1744
B20: EXECUTIVE RECOMMENDATION
B21: The Digital Transformation initiative demonstrates a positive NPV under Base and Optimistic scenarios, with a benefit-cost ratio above 1.0x confirming value creation over the analysis horizon. The primary risk is benefit realisation timing, addressed through conservative ramp-up assumptions in Year 1–2. The Board is recommended to approve the investment, subject to phased milestone gates and quarterly benefit tracking against this model.

Sheet Audit Checks
B2: MODEL AUDIT & INTEGRITY CHECKS
B4: STRUCTURAL CHECKS
B5: Check Description | C5: Formula / Result | D5: Status
B6: Total Benefits > 0 (Base Case) | C6: ='Cost-Benefit'!K26 -> 14003.661 | D6: =IF(C6>0,"PASS","FAIL") -> PASS
B7: Total Costs > 0 | C7: ='Cost-Benefit'!K20 -> 5555.4864 | D7: =IF(C7>0,"PASS","FAIL") -> PASS
B8: Discount Rate is between 1%-20% | C8: =Assumptions!D11 -> 0.07 | D8: =IF(C8>0,"PASS","FAIL") -> PASS
B9: No negative discount factors | C9: =MIN('Cost-Benefit'!D30:J30) -> 0.66634222 | D9: =IF(C9>0,"PASS","FAIL") -> PASS
B10: BCR > 1 (value accretive – Base) | C10: ='Cost-Benefit'!C39 -> 2.5206903 | D10: =IF(C10>0,"PASS","FAIL") -> PASS
B13: MODEL SUMMARY
B14: Active Scenario | C14: =Assumptions!C5 -> Base Case
B15: NPV (Base) | C15: ='Cost-Benefit'!C35 -> 6124.6368
B16: IRR (Base) | C16: ='Cost-Benefit'!C36 -> 0.66538209
B17: Payback Period | C17: ='Cost-Benefit'!C40 -> Review
B18: Model Prepared by | C18: Nathan Wallis
B19: Last Updated | C19: June 2026
